xai/__init__.py
xai/constants.py
xai/exception.py
xai/util.py
xai/compiler/__init__.py
xai/compiler/base.py
xai/compiler/data.py
xai/compiler/evaluation.py
xai/compiler/explainer.py
xai/compiler/features.py
xai/compiler/model.py
xai/compiler/validator.py
xai/compiler/writer.py
xai/data/__init__.py
xai/data/abstract_stats.py
xai/data/constants.py
xai/data/exceptions.py
xai/data/helper.py
xai/data/explorer/__init__.py
xai/data/explorer/abstract_analyzer.py
xai/data/explorer/abstract_labelled_analyzer.py
xai/data/explorer/data_analyzer_suite.py
xai/data/explorer/sequence_analyzer.py
xai/data/explorer/categorical/__init__.py
xai/data/explorer/categorical/categorical_analyzer.py
xai/data/explorer/categorical/categorical_stats.py
xai/data/explorer/categorical/labelled_categorical_analyzer.py
xai/data/explorer/datetime/__init__.py
xai/data/explorer/datetime/datetime_analyzer.py
xai/data/explorer/datetime/datetime_stats.py
xai/data/explorer/datetime/labelled_datetime_analyzer.py
xai/data/explorer/numerical/__init__.py
xai/data/explorer/numerical/labelled_numerical_analyzer.py
xai/data/explorer/numerical/numerical_analyzer.py
xai/data/explorer/numerical/numerical_stats.py
xai/data/explorer/text/__init__.py
xai/data/explorer/text/labelled_text_analyzer.py
xai/data/explorer/text/text_analyzer.py
xai/data/explorer/text/text_stats.py
xai/data/tokenizers/punkt/PY3/english.pickle
xai/data/tokenizers/punkt/PY3/french.pickle
xai/data/tokenizers/punkt/PY3/german.pickle
xai/data/tokenizers/punkt/PY3/russian.pickle
xai/data/tokenizers/punkt/PY3/spanish.pickle
xai/data/validator/__init__.py
xai/data/validator/abstract_validator.py
xai/data/validator/dataframe_validator.py
xai/data/validator/enum_validator.py
xai/data/validator/missing_validator.py
xai/data/validator/validation_stats.py
xai/explainer/__init__.py
xai/explainer/abstract_explainer.py
xai/explainer/config.py
xai/explainer/constants.py
xai/explainer/explainer_exceptions.py
xai/explainer/explainer_factory.py
contextual_ai-0.0.2.dist-info/LICENSE
contextual_ai-0.0.2.dist-info/METADATA
contextual_ai-0.0.2.dist-info/WHEEL
contextual_ai-0.0.2.dist-info/top_level.txt
contextual_ai-0.0.2.dist-info/RECORD
