Metadata-Version: 2.1
Name: contextual-ai
Version: 0.0.2
Summary: Contextual AI
Home-page: https://github.com/SAP/contextual-ai.git
Author: SAP
License: UNKNOWN
Project-URL: Documentation, https://contextual-ai.readthedocs.io/en/latest/
Platform: any
Classifier: Programming Language :: Python :: 3.6
Classifier: Programming Language :: Python :: 3.7
Classifier: Programming Language :: Python :: 3.8
Classifier: Operating System :: OS Independent
Classifier: Topic :: Software Development :: Libraries :: Python Modules
Classifier: Topic :: Scientific/Engineering :: Artificial Intelligence
Classifier: License :: OSI Approved :: Apache Software License
Requires-Dist: ipython
Requires-Dist: numpy (>=1.18.2)
Requires-Dist: pandas (>=0.25.1)
Requires-Dist: scikit-learn (==0.22.2)
Requires-Dist: scipy (>=1.3.1)
Requires-Dist: tqdm (>=4.44.1)
Requires-Dist: matplotlib (>=3.1.2)
Requires-Dist: seaborn (>=0.9.0)
Requires-Dist: fpdf (==1.7.2)
Requires-Dist: wordcloud (==1.5.0)
Requires-Dist: nltk (==3.4.5)
Requires-Dist: ordered-set (>=3.1.0)
Requires-Dist: lime (<=2,>=0.1.1)
Requires-Dist: dill (>=0.3.0)
Requires-Dist: shap (>=0.35.0)
Requires-Dist: yattag (==1.12.2)
Requires-Dist: pyyaml (==5.3.1)
Requires-Dist: pillow (>=7.1.0)
Requires-Dist: jsonschema (==3.0.2)
Requires-Dist: PyPDF2 (==1.26.0)
